[
  {
    "name": "ABDUL WAFI",
    "stock": 0,
    "isTokenValid": true,
    "isAlive": true,
    "lastUpdate": "2024-12-24T09:39:18.090Z"
  },
  {
    "name": "AKBAR RISQ",
    "stock": 0,
    "isTokenValid": true,
    "isAlive": true,
    "lastUpdate": "2024-12-24T09:34:17.547Z"
  },
  {
    "name": "ALFIAN DWI A.",
    "stock": 0,
    "isTokenValid": true,
    "isAlive": true,
    "lastUpdate": "2024-12-24T09:34:18.414Z"
  },
  {
    "name": "ATHI HANDAYANI",
    "stock": 0,
    "isTokenValid": true,
    "isAlive": true,
    "lastUpdate": "2024-12-24T09:34:19.469Z"
  },
  {
    "name": "CINDRAWATI",
    "stock": 0,
    "isTokenValid": true,
    "isAlive": true,
    "lastUpdate": "2024-12-24T09:34:20.276Z"
  },
  {
    "name": "EDI SUGENG SARIPAN",
    "stock": 0,
    "isTokenValid": true,
    "isAlive": true,
    "lastUpdate": "2024-12-24T09:34:21.225Z"
  },
  {
    "name": "BINA MAKMUR",
    "stock": 0,
    "isTokenValid": true,
    "isAlive": true,
    "lastUpdate": "2024-12-24T09:34:22.533Z"
  },
  {
    "name": "HENDRA KURNIAWAN",
    "stock": 0,
    "isTokenValid": true,
    "isAlive": true,
    "lastUpdate": "2024-12-24T09:34:23.470Z"
  },
  {
    "name": "SUCIYONO",
    "stock": 0,
    "isTokenValid": true,
    "isAlive": true,
    "lastUpdate": "2024-12-24T09:34:24.585Z"
  },
  {
    "name": "SUMBER REJEKI",
    "stock": 0,
    "isTokenValid": true,
    "isAlive": true,
    "lastUpdate": "2024-12-24T09:34:25.837Z"
  },
  {
    "name": "JAENAL",
    "stock": 0,
    "isTokenValid": true,
    "isAlive": true,
    "lastUpdate": "2024-12-24T09:34:26.569Z"
  },
  {
    "name": "JOKO SUWARNO",
    "stock": 0,
    "isTokenValid": true,
    "isAlive": true,
    "lastUpdate": "2024-12-24T09:34:27.406Z"
  },
  {
    "name": "KARSONO",
    "stock": 0,
    "isTokenValid": true,
    "isAlive": true,
    "lastUpdate": "2024-12-24T09:34:28.282Z"
  },
  {
    "name": "LUTFI A.",
    "stock": 0,
    "isTokenValid": true,
    "isAlive": true,
    "lastUpdate": "2024-12-24T09:34:31.625Z"
  },
  {
    "name": "MOH SAID",
    "stock": 0,
    "isTokenValid": true,
    "isAlive": true,
    "lastUpdate": "2024-12-24T09:34:33.892Z"
  },
  {
    "name": "TITIK ISMIATIN",
    "stock": 0,
    "isTokenValid": true,
    "isAlive": true,
    "lastUpdate": "2024-12-24T09:34:36.371Z"
  },
  {
    "name": "TK. MAJU",
    "stock": 0,
    "isTokenValid": true,
    "isAlive": true,
    "lastUpdate": "2024-12-24T09:34:39.043Z"
  },
  {
    "name": "TOKO 2 PUTRI",
    "stock": 0,
    "isTokenValid": true,
    "isAlive": true,
    "lastUpdate": "2024-12-24T09:34:40.389Z"
  },
  {
    "name": "TOKO IIN",
    "stock": 0,
    "isTokenValid": true,
    "isAlive": true,
    "lastUpdate": "2024-12-24T09:34:43.382Z"
  },
  {
    "name": "TOKO POJOK",
    "stock": 0,
    "isTokenValid": true,
    "isAlive": true,
    "lastUpdate": "2024-12-24T09:34:44.293Z"
  },
  {
    "name": "UD RAHMAT",
    "stock": 0,
    "isTokenValid": true,
    "isAlive": true,
    "lastUpdate": "2024-12-24T09:34:45.867Z"
  },
  {
    "name": "SUPARMAN",
    "stock": 0,
    "isTokenValid": true,
    "isAlive": true,
    "lastUpdate": "2024-12-24T09:34:46.628Z"
  },
  {
    "name": "DJAMIAH",
    "stock": 0,
    "isTokenValid": true,
    "isAlive": true,
    "lastUpdate": "2024-12-24T09:34:47.370Z"
  },
  {
    "name": "HJ LILIK LAILIYAH",
    "stock": 0,
    "isTokenValid": true,
    "isAlive": true,
    "lastUpdate": "2024-12-24T09:34:48.199Z"
  },
  {
    "name": "ERNA PUJIATI",
    "stock": 0,
    "isTokenValid": true,
    "isAlive": true,
    "lastUpdate": "2024-12-24T09:34:49.055Z"
  },
  {
    "name": "P. SUK",
    "stock": 0,
    "isTokenValid": false,
    "isAlive": true,
    "lastUpdate": "2024-12-24T09:34:49.789Z"
  },
  {
    "name": "H. BAMBANG S",
    "stock": 0,
    "isTokenValid": false,
    "isAlive": true,
    "lastUpdate": "2024-12-24T09:34:50.585Z"
  },
  {
    "name": "ANDRI HERU CAHYONO",
    "stock": 0,
    "isTokenValid": false,
    "isAlive": true,
    "lastUpdate": "2024-12-24T09:34:51.323Z"
  },
  {
    "name": "JONI H",
    "stock": 0,
    "isTokenValid": false,
    "isAlive": true,
    "lastUpdate": "2024-12-24T09:34:52.058Z"
  },
  {
    "name": "EVI DIANA SARI",
    "stock": 0,
    "isTokenValid": true,
    "isAlive": true,
    "lastUpdate": "2024-12-24T09:34:52.802Z"
  },
  {
    "name": "TOKO IRAWAN",
    "stock": 0,
    "isTokenValid": true,
    "isAlive": true,
    "lastUpdate": "2024-12-24T09:34:53.545Z"
  },
  {
    "name": "TK MUSTAPA",
    "stock": 0,
    "isTokenValid": true,
    "isAlive": true,
    "lastUpdate": "2024-12-24T09:34:54.326Z"
  },
  {
    "name": "YUNIS WAHYUNI",
    "stock": 0,
    "isTokenValid": true,
    "isAlive": true,
    "lastUpdate": "2024-12-24T09:34:55.048Z"
  },
  {
    "name": "ROSA V",
    "stock": 0,
    "isTokenValid": true,
    "isAlive": true,
    "lastUpdate": "2024-12-24T09:34:55.797Z"
  },
  {
    "name": "LUKMAN BS",
    "stock": 0,
    "isTokenValid": true,
    "isAlive": true,
    "lastUpdate": "2024-12-24T09:34:56.659Z"
  },
  {
    "name": "BISTON MANURUNG",
    "stock": 0,
    "isTokenValid": true,
    "isAlive": true,
    "lastUpdate": "2024-12-24T09:34:57.454Z"
  },
  {
    "name": "ROSIDI",
    "stock": 0,
    "isTokenValid": true,
    "isAlive": true,
    "lastUpdate": "2024-12-24T09:34:58.249Z"
  },
  {
    "name": "ALPAN SANYOTO",
    "stock": 0,
    "isTokenValid": false,
    "isAlive": true,
    "lastUpdate": "2024-12-24T09:34:58.962Z"
  },
  {
    "name": "JAMILAH",
    "stock": 0,
    "isTokenValid": true,
    "isAlive": true,
    "lastUpdate": "2024-12-24T09:34:59.743Z"
  },
  {
    "name": "YUDA",
    "stock": 0,
    "isTokenValid": true,
    "isAlive": true,
    "lastUpdate": "2024-12-24T09:35:00.627Z"
  },
  {
    "name": "SRI UTAMI",
    "stock": 0,
    "isTokenValid": true,
    "isAlive": true,
    "lastUpdate": "2024-12-24T09:35:01.470Z"
  },
  {
    "name": "ULFA MARIA",
    "stock": 0,
    "isTokenValid": true,
    "isAlive": true,
    "lastUpdate": "2024-12-24T09:35:02.221Z"
  },
  {
    "name": "BAMBANG HARTONO",
    "stock": 0,
    "isTokenValid": true,
    "isAlive": true,
    "lastUpdate": "2024-12-24T09:35:02.999Z"
  },
  {
    "name": "HJ. ASLAMIYAH",
    "stock": 0,
    "isTokenValid": true,
    "isAlive": true,
    "lastUpdate": "2024-12-24T09:35:03.763Z"
  },
  {
    "name": "NADIFATUS SOLEHA",
    "stock": 0,
    "isTokenValid": true,
    "isAlive": true,
    "lastUpdate": "2024-12-24T09:35:04.516Z"
  },
  {
    "name": "ISTIQOMAH",
    "stock": 0,
    "isTokenValid": true,
    "isAlive": true,
    "lastUpdate": "2024-12-24T09:35:05.249Z"
  },
  {
    "name": "SUROSO",
    "stock": 0,
    "isTokenValid": true,
    "isAlive": true,
    "lastUpdate": "2024-12-24T09:35:06.140Z"
  },
  {
    "name": "HADI SUTOYO",
    "stock": 0,
    "isTokenValid": true,
    "isAlive": true,
    "lastUpdate": "2024-12-24T09:35:06.875Z"
  },
  {
    "name": "SRI HIDAYATI",
    "stock": 0,
    "isTokenValid": true,
    "isAlive": true,
    "lastUpdate": "2024-12-24T09:35:07.679Z"
  },
  {
    "name": "ONG SWI GIOK",
    "stock": 0,
    "isTokenValid": true,
    "isAlive": true,
    "lastUpdate": "2024-12-24T09:35:08.427Z"
  },
  {
    "name": "YUSUF ISMAIL",
    "stock": 0,
    "isTokenValid": true,
    "isAlive": true,
    "lastUpdate": "2024-12-24T09:35:09.189Z"
  },
  {
    "name": "SUPARNI",
    "stock": 0,
    "isTokenValid": true,
    "isAlive": true,
    "lastUpdate": "2024-12-24T09:35:09.957Z"
  },
  {
    "name": "H. JUMAT",
    "stock": 0,
    "isTokenValid": true,
    "isAlive": true,
    "lastUpdate": "2024-12-24T09:39:18.905Z"
  },
  {
    "name": "YOGA RAJAN",
    "stock": 0,
    "isTokenValid": true,
    "isAlive": true,
    "lastUpdate": "2024-12-24T09:35:10.831Z"
  },
  {
    "name": "HARSININGSIH",
    "stock": 3,
    "isTokenValid": true,
    "isAlive": false,
    "lastUpdate": "2024-12-24T09:35:11.634Z"
  },
  {
    "name": "ARIF FAUZI",
    "stock": 0,
    "isTokenValid": true,
    "isAlive": true,
    "lastUpdate": "2024-12-24T09:35:13.025Z"
  },
  {
    "name": "TOKO SURYATI",
    "stock": 26,
    "isTokenValid": true,
    "isAlive": true,
    "lastUpdate": "2024-12-24T09:44:18.233Z"
  },
  {
    "name": "MOH HAFIF",
    "stock": 0,
    "isTokenValid": true,
    "isAlive": true,
    "lastUpdate": "2024-12-24T09:35:55.313Z"
  },
  {
    "name": "CAHYA HERAWATI",
    "stock": 0,
    "isTokenValid": true,
    "isAlive": true,
    "lastUpdate": "2024-12-24T09:35:56.058Z"
  },
  {
    "name": "SUDJIONO",
    "stock": 0,
    "isTokenValid": true,
    "isAlive": true,
    "lastUpdate": "2024-12-24T09:35:56.795Z"
  },
  {
    "name": "SAMSUL ARIFIN",
    "stock": 0,
    "isTokenValid": true,
    "isAlive": true,
    "lastUpdate": "2024-12-24T09:35:57.555Z"
  },
  {
    "name": "WIKAN K",
    "stock": 0,
    "isTokenValid": true,
    "isAlive": true,
    "lastUpdate": "2024-12-24T09:35:58.382Z"
  },
  {
    "name": "TUSOK",
    "stock": 0,
    "isTokenValid": true,
    "isAlive": true,
    "lastUpdate": "2024-12-24T09:35:59.116Z"
  },
  {
    "name": "MISRI CICI",
    "stock": 0,
    "isTokenValid": true,
    "isAlive": true,
    "lastUpdate": "2024-12-24T09:35:59.905Z"
  },
  {
    "name": "HERDIANA DIYAH S",
    "stock": 0,
    "isTokenValid": true,
    "isAlive": true,
    "lastUpdate": "2024-12-24T09:36:00.735Z"
  },
  {
    "name": "BUDI",
    "stock": 0,
    "isTokenValid": true,
    "isAlive": true,
    "lastUpdate": "2024-12-24T09:36:01.657Z"
  },
  {
    "name": "YULI SORAYA",
    "stock": 0,
    "isTokenValid": true,
    "isAlive": true,
    "lastUpdate": "2024-12-24T09:36:02.409Z"
  },
  {
    "name": "SUSILO",
    "stock": 0,
    "isTokenValid": true,
    "isAlive": true,
    "lastUpdate": "2024-12-24T09:36:03.162Z"
  },
  {
    "name": "HJ. HAERONI",
    "stock": 0,
    "isTokenValid": true,
    "isAlive": true,
    "lastUpdate": "2024-12-24T09:36:03.893Z"
  },
  {
    "name": "IMA",
    "stock": 0,
    "isTokenValid": true,
    "isAlive": true,
    "lastUpdate": "2024-12-24T09:36:04.666Z"
  },
  {
    "name": "DARMAWAN P",
    "stock": 0,
    "isTokenValid": true,
    "isAlive": true,
    "lastUpdate": "2024-12-24T09:36:05.395Z"
  },
  {
    "name": "DIYAH UTAMI",
    "stock": 10,
    "isTokenValid": true,
    "isAlive": true,
    "lastUpdate": "2024-12-24T09:44:59.849Z"
  },
  {
    "name": "SALMAH",
    "stock": 46,
    "isTokenValid": true,
    "isAlive": true,
    "lastUpdate": "2024-12-24T09:45:30.523Z"
  },
  {
    "name": "TOKO ANITA",
    "stock": 0,
    "isTokenValid": true,
    "isAlive": true,
    "lastUpdate": "2024-12-24T09:37:14.995Z"
  },
  {
    "name": "TK. LUCKY",
    "stock": 0,
    "isTokenValid": true,
    "isAlive": true,
    "lastUpdate": "2024-12-24T09:37:15.819Z"
  },
  {
    "name": "UD SAMAN HADI",
    "stock": 0,
    "isTokenValid": true,
    "isAlive": true,
    "lastUpdate": "2024-12-24T09:37:16.583Z"
  },
  {
    "name": "SOEKAMTO",
    "stock": 13,
    "isTokenValid": true,
    "isAlive": true,
    "lastUpdate": "2024-12-24T09:46:09.809Z"
  },
  {
    "name": "TOKO TIARA",
    "stock": 0,
    "isTokenValid": true,
    "isAlive": true,
    "lastUpdate": "2024-12-24T09:37:47.393Z"
  },
  {
    "name": "TOKO POJOK-DISABLE",
    "stock": 100,
    "isTokenValid": true,
    "isAlive": false,
    "lastUpdate": "2024-10-27T12:14:33.083Z"
  },
  {
    "name": "TOKO ANITA-DISABLE",
    "stock": 65,
    "isTokenValid": true,
    "isAlive": false,
    "lastUpdate": "2024-11-09T11:04:53.417Z"
  },
  {
    "name": "UD SAMAN HADI-DISABLE",
    "stock": 5,
    "isTokenValid": true,
    "isAlive": false,
    "lastUpdate": "2024-11-09T11:04:54.985Z"
  }
]