[
  {
    "name": "ABDUL WAFI",
    "stock": 0,
    "isTokenValid": true,
    "isAlive": true,
    "lastUpdate": "2025-06-18T10:43:42.435Z"
  },
  {
    "name": "AKBAR RISQ",
    "stock": 0,
    "isTokenValid": true,
    "isAlive": true,
    "lastUpdate": "2025-06-18T10:43:46.098Z"
  },
  {
    "name": "ALFIAN DWI A.",
    "stock": 0,
    "isTokenValid": true,
    "isAlive": true,
    "lastUpdate": "2025-06-18T10:43:50.755Z"
  },
  {
    "name": "ATHI HANDAYANI",
    "stock": 0,
    "isTokenValid": true,
    "isAlive": true,
    "lastUpdate": "2025-06-18T10:43:54.092Z"
  },
  {
    "name": "CINDRAWATI",
    "stock": 0,
    "isTokenValid": true,
    "isAlive": true,
    "lastUpdate": "2025-06-18T10:44:15.559Z"
  },
  {
    "name": "EDI SUGENG SARIPAN",
    "stock": 0,
    "isTokenValid": true,
    "isAlive": true,
    "lastUpdate": "2025-06-18T10:44:36.211Z"
  },
  {
    "name": "BINA MAKMUR",
    "stock": 0,
    "isTokenValid": true,
    "isAlive": true,
    "lastUpdate": "2025-06-18T10:44:39.879Z"
  },
  {
    "name": "HENDRA KURNIAWAN",
    "stock": 0,
    "isTokenValid": true,
    "isAlive": true,
    "lastUpdate": "2025-06-18T10:44:43.272Z"
  },
  {
    "name": "SUCIYONO",
    "stock": 0,
    "isTokenValid": true,
    "isAlive": true,
    "lastUpdate": "2025-06-18T10:44:46.777Z"
  },
  {
    "name": "SUMBER REJEKI",
    "stock": 0,
    "isTokenValid": true,
    "isAlive": true,
    "lastUpdate": "2025-06-18T10:44:50.294Z"
  },
  {
    "name": "JAENAL",
    "stock": 0,
    "isTokenValid": true,
    "isAlive": true,
    "lastUpdate": "2025-06-18T10:44:53.545Z"
  },
  {
    "name": "JOKO SUWARNO",
    "stock": 0,
    "isTokenValid": true,
    "isAlive": true,
    "lastUpdate": "2025-06-18T10:44:57.015Z"
  },
  {
    "name": "KARSONO",
    "stock": 0,
    "isTokenValid": true,
    "isAlive": true,
    "lastUpdate": "2025-06-18T10:47:59.692Z"
  },
  {
    "name": "LUTFI A.",
    "stock": 0,
    "isTokenValid": true,
    "isAlive": true,
    "lastUpdate": "2025-06-18T10:45:02.400Z"
  },
  {
    "name": "MOH SAID",
    "stock": 0,
    "isTokenValid": true,
    "isAlive": true,
    "lastUpdate": "2025-06-18T10:45:06.200Z"
  },
  {
    "name": "TITIK ISMIATIN",
    "stock": 0,
    "isTokenValid": true,
    "isAlive": true,
    "lastUpdate": "2025-06-18T10:45:09.850Z"
  },
  {
    "name": "TK. MAJU",
    "stock": 0,
    "isTokenValid": true,
    "isAlive": true,
    "lastUpdate": "2025-06-18T10:45:15.630Z"
  },
  {
    "name": "TOKO 2 PUTRI",
    "stock": 0,
    "isTokenValid": true,
    "isAlive": true,
    "lastUpdate": "2025-06-18T10:45:20.399Z"
  },
  {
    "name": "TOKO IIN",
    "stock": 0,
    "isTokenValid": true,
    "isAlive": true,
    "lastUpdate": "2025-06-18T10:45:25.801Z"
  },
  {
    "name": "TOKO POJOK",
    "stock": 0,
    "isTokenValid": true,
    "isAlive": true,
    "lastUpdate": "2025-06-18T10:45:29.184Z"
  },
  {
    "name": "UD RAHMAT",
    "stock": 0,
    "isTokenValid": true,
    "isAlive": true,
    "lastUpdate": "2025-06-18T10:45:32.868Z"
  },
  {
    "name": "SUPARMAN",
    "stock": 0,
    "isTokenValid": true,
    "isAlive": true,
    "lastUpdate": "2025-06-18T11:12:28.852Z"
  },
  {
    "name": "DJAMIAH",
    "stock": 0,
    "isTokenValid": true,
    "isAlive": true,
    "lastUpdate": "2025-01-31T11:09:19.056Z"
  },
  {
    "name": "HJ LILIK LAILIYAH",
    "stock": 0,
    "isTokenValid": true,
    "isAlive": true,
    "lastUpdate": "2025-06-18T10:45:36.212Z"
  },
  {
    "name": "ERNA PUJIATI",
    "stock": 0,
    "isTokenValid": true,
    "isAlive": true,
    "lastUpdate": "2025-06-18T10:45:39.577Z"
  },
  {
    "name": "P. SUK",
    "stock": 0,
    "isTokenValid": true,
    "isAlive": true,
    "lastUpdate": "2025-06-18T10:45:42.903Z"
  },
  {
    "name": "H. BAMBANG S",
    "stock": 0,
    "isTokenValid": true,
    "isAlive": true,
    "lastUpdate": "2025-01-31T15:51:34.327Z"
  },
  {
    "name": "ANDRI HERU CAHYONO",
    "stock": 0,
    "isTokenValid": true,
    "isAlive": true,
    "lastUpdate": "2025-06-18T10:45:47.161Z"
  },
  {
    "name": "JONI H",
    "stock": 0,
    "isTokenValid": true,
    "isAlive": true,
    "lastUpdate": "2025-06-18T10:45:50.573Z"
  },
  {
    "name": "EVI DIANA SARI",
    "stock": 0,
    "isTokenValid": true,
    "isAlive": true,
    "lastUpdate": "2025-01-31T09:35:29.570Z"
  },
  {
    "name": "TOKO IRAWAN",
    "stock": 0,
    "isTokenValid": true,
    "isAlive": true,
    "lastUpdate": "2025-06-18T10:45:53.915Z"
  },
  {
    "name": "TK MUSTAPA",
    "stock": 0,
    "isTokenValid": true,
    "isAlive": true,
    "lastUpdate": "2025-02-08T20:41:25.946Z"
  },
  {
    "name": "YUNIS WAHYUNI",
    "stock": 0,
    "isTokenValid": true,
    "isAlive": true,
    "lastUpdate": "2025-06-18T10:45:57.210Z"
  },
  {
    "name": "ROSA V",
    "stock": 0,
    "isTokenValid": true,
    "isAlive": true,
    "lastUpdate": "2025-06-18T10:46:00.501Z"
  },
  {
    "name": "LUKMAN BS",
    "stock": 0,
    "isTokenValid": true,
    "isAlive": true,
    "lastUpdate": "2025-06-18T10:46:03.901Z"
  },
  {
    "name": "BISTON MANURUNG",
    "stock": 0,
    "isTokenValid": true,
    "isAlive": true,
    "lastUpdate": "2025-06-18T10:46:07.398Z"
  },
  {
    "name": "ROSIDI",
    "stock": 0,
    "isTokenValid": true,
    "isAlive": true,
    "lastUpdate": "2025-06-18T10:46:10.747Z"
  },
  {
    "name": "ALPAN SANYOTO",
    "stock": 0,
    "isTokenValid": false,
    "isAlive": true,
    "lastUpdate": "2025-01-18T16:42:57.076Z"
  },
  {
    "name": "JAMILAH",
    "stock": 0,
    "isTokenValid": true,
    "isAlive": true,
    "lastUpdate": "2025-06-18T10:46:14.064Z"
  },
  {
    "name": "YUDA",
    "stock": 0,
    "isTokenValid": true,
    "isAlive": true,
    "lastUpdate": "2025-06-18T10:46:17.493Z"
  },
  {
    "name": "SRI UTAMI",
    "stock": 0,
    "isTokenValid": true,
    "isAlive": true,
    "lastUpdate": "2025-06-18T10:46:20.785Z"
  },
  {
    "name": "ULFA MARIA",
    "stock": 0,
    "isTokenValid": true,
    "isAlive": true,
    "lastUpdate": "2025-06-18T10:46:24.123Z"
  },
  {
    "name": "BAMBANG HARTONO",
    "stock": 0,
    "isTokenValid": true,
    "isAlive": true,
    "lastUpdate": "2025-06-18T10:46:27.427Z"
  },
  {
    "name": "HJ. ASLAMIYAH",
    "stock": 0,
    "isTokenValid": true,
    "isAlive": true,
    "lastUpdate": "2025-06-18T10:46:30.730Z"
  },
  {
    "name": "NADIFATUS SOLEHA",
    "stock": 0,
    "isTokenValid": true,
    "isAlive": true,
    "lastUpdate": "2025-06-18T10:46:34.048Z"
  },
  {
    "name": "ISTIQOMAH",
    "stock": 0,
    "isTokenValid": true,
    "isAlive": true,
    "lastUpdate": "2025-06-18T10:46:37.328Z"
  },
  {
    "name": "SUROSO",
    "stock": 0,
    "isTokenValid": true,
    "isAlive": true,
    "lastUpdate": "2025-06-18T10:46:40.654Z"
  },
  {
    "name": "HADI SUTOYO",
    "stock": 0,
    "isTokenValid": true,
    "isAlive": true,
    "lastUpdate": "2025-06-18T10:46:44.022Z"
  },
  {
    "name": "SRI HIDAYATI",
    "stock": 0,
    "isTokenValid": true,
    "isAlive": true,
    "lastUpdate": "2025-06-18T11:07:27.066Z"
  },
  {
    "name": "ONG SWI GIOK",
    "stock": 0,
    "isTokenValid": true,
    "isAlive": true,
    "lastUpdate": "2025-06-18T11:07:30.049Z"
  },
  {
    "name": "YUSUF ISMAIL",
    "stock": 0,
    "isTokenValid": true,
    "isAlive": true,
    "lastUpdate": "2025-06-18T11:07:32.924Z"
  },
  {
    "name": "SUPARNI",
    "stock": 0,
    "isTokenValid": true,
    "isAlive": true,
    "lastUpdate": "2025-06-18T10:46:47.291Z"
  },
  {
    "name": "H. JUMAT",
    "stock": 0,
    "isTokenValid": true,
    "isAlive": true,
    "lastUpdate": "2025-06-18T11:07:35.735Z"
  },
  {
    "name": "YOGA RAJAN",
    "stock": 0,
    "isTokenValid": true,
    "isAlive": true,
    "lastUpdate": "2025-06-18T11:07:38.523Z"
  },
  {
    "name": "HARSININGSIH",
    "stock": 0,
    "isTokenValid": true,
    "isAlive": true,
    "lastUpdate": "2025-06-18T11:07:41.173Z"
  },
  {
    "name": "ARIF FAUZI",
    "stock": 0,
    "isTokenValid": true,
    "isAlive": true,
    "lastUpdate": "2025-06-18T10:46:50.627Z"
  },
  {
    "name": "TOKO SURYATI",
    "stock": 0,
    "isTokenValid": true,
    "isAlive": true,
    "lastUpdate": "2025-06-18T11:07:43.968Z"
  },
  {
    "name": "MOH HAFIF",
    "stock": 0,
    "isTokenValid": true,
    "isAlive": true,
    "lastUpdate": "2025-06-18T11:08:30.554Z"
  },
  {
    "name": "CAHYA HERAWATI",
    "stock": 0,
    "isTokenValid": true,
    "isAlive": true,
    "lastUpdate": "2025-06-18T11:08:33.398Z"
  },
  {
    "name": "SUDJIONO",
    "stock": 0,
    "isTokenValid": true,
    "isAlive": true,
    "lastUpdate": "2025-06-18T11:08:36.162Z"
  },
  {
    "name": "SAMSUL ARIFIN",
    "stock": 0,
    "isTokenValid": true,
    "isAlive": true,
    "lastUpdate": "2025-06-18T10:53:55.924Z"
  },
  {
    "name": "WIKAN K",
    "stock": 0,
    "isTokenValid": true,
    "isAlive": true,
    "lastUpdate": "2025-06-18T10:48:46.294Z"
  },
  {
    "name": "TUSOK",
    "stock": 0,
    "isTokenValid": true,
    "isAlive": true,
    "lastUpdate": "2025-06-18T11:08:38.942Z"
  },
  {
    "name": "MISRI CICI",
    "stock": 0,
    "isTokenValid": true,
    "isAlive": true,
    "lastUpdate": "2025-06-18T11:11:43.590Z"
  },
  {
    "name": "HERDIANA DIYAH S",
    "stock": 0,
    "isTokenValid": true,
    "isAlive": true,
    "lastUpdate": "2025-06-18T10:49:31.561Z"
  },
  {
    "name": "BUDI",
    "stock": 0,
    "isTokenValid": true,
    "isAlive": true,
    "lastUpdate": "2025-06-18T10:49:34.943Z"
  },
  {
    "name": "YULI SORAYA",
    "stock": 0,
    "isTokenValid": true,
    "isAlive": true,
    "lastUpdate": "2025-06-18T10:49:38.285Z"
  },
  {
    "name": "SUSILO",
    "stock": 0,
    "isTokenValid": true,
    "isAlive": true,
    "lastUpdate": "2025-06-18T10:49:41.651Z"
  },
  {
    "name": "HJ. HAERONI",
    "stock": 0,
    "isTokenValid": true,
    "isAlive": true,
    "lastUpdate": "2025-06-18T10:49:45.010Z"
  },
  {
    "name": "IMA",
    "stock": 0,
    "isTokenValid": true,
    "isAlive": true,
    "lastUpdate": "2025-06-18T10:49:48.349Z"
  },
  {
    "name": "DARMAWAN P",
    "stock": 0,
    "isTokenValid": true,
    "isAlive": true,
    "lastUpdate": "2025-06-18T10:49:51.681Z"
  },
  {
    "name": "DIYAH UTAMI",
    "stock": 0,
    "isTokenValid": true,
    "isAlive": true,
    "lastUpdate": "2025-06-18T10:49:54.977Z"
  },
  {
    "name": "SALMAH",
    "stock": 0,
    "isTokenValid": true,
    "isAlive": true,
    "lastUpdate": "2025-06-18T10:49:58.307Z"
  },
  {
    "name": "TOKO ANITA",
    "stock": 0,
    "isTokenValid": true,
    "isAlive": true,
    "lastUpdate": "2025-06-18T10:50:01.857Z"
  },
  {
    "name": "TK. LUCKY",
    "stock": 0,
    "isTokenValid": true,
    "isAlive": true,
    "lastUpdate": "2025-06-18T10:50:05.290Z"
  },
  {
    "name": "UD SAMAN HADI",
    "stock": 0,
    "isTokenValid": true,
    "isAlive": true,
    "lastUpdate": "2025-06-18T10:50:08.656Z"
  },
  {
    "name": "SOEKAMTO",
    "stock": 0,
    "isTokenValid": true,
    "isAlive": true,
    "lastUpdate": "2025-06-18T10:50:12.061Z"
  },
  {
    "name": "TOKO TIARA",
    "stock": 0,
    "isTokenValid": true,
    "isAlive": true,
    "lastUpdate": "2025-06-18T10:50:15.543Z"
  },
  {
    "name": "TOKO POJOK-DISABLE",
    "stock": 100,
    "isTokenValid": true,
    "isAlive": false,
    "lastUpdate": "2024-10-27T12:14:33.083Z"
  },
  {
    "name": "TOKO ANITA-DISABLE",
    "stock": 0,
    "isTokenValid": true,
    "isAlive": true,
    "lastUpdate": "2024-12-31T10:52:30.554Z"
  },
  {
    "name": "UD SAMAN HADI-DISABLE",
    "stock": 0,
    "isTokenValid": false,
    "isAlive": true,
    "lastUpdate": "2024-12-31T10:52:32.111Z"
  },
  {
    "name": "TK MUSTAPA-DISABLED",
    "stock": 0,
    "isTokenValid": true,
    "isAlive": true,
    "lastUpdate": "2025-02-09T08:26:47.731Z"
  }
]